tgtypes/__init__.py
tgtypes/chat.py
tgtypes/descriptors/__init__.py
tgtypes/descriptors/base.py
tgtypes/descriptors/chat_descriptor.py
tgtypes/identities/__init__.py
tgtypes/identities/chat_identity.py
tgtypes/identities/message_identity.py
tgtypes/interfaces/__init__.py
tgtypes/interfaces/chatresolver.py
tgtypes/message.py
tgtypes/persistence/__init__.py
tgtypes/persistence/textmessagemodel.py
tgtypes/primitives.py
tgtypes/textmessagemodel.py
tgtypes/update.py
tgtypes/update_field_extractor.py
tgtypes/user.py
tgtypes/utils/__init__.py
tgtypes/utils/async_lazy_dict.py
tgtypes-0.1.1.dist-info/LICENSE
tgtypes-0.1.1.dist-info/WHEEL
tgtypes-0.1.1.dist-info/METADATA
tgtypes-0.1.1.dist-info/RECORD
